pysonyavr
