Metadata-Version: 1.0
Name: pysonyavr
Version: 1.3
Summary: Python bindings for modern Sony speakers
Home-page: https://github.com/pschmitt/pysonyavr
Author: Philipp Schmitt
Author-email: philipp@schmitt.co
License: GPL3
Platform: UNKNOWN
